textformer/__init__.py
textformer/core/__init__.py
textformer/core/model.py
textformer/datasets/__init__.py
textformer/datasets/generative.py
textformer/datasets/translation.py
textformer/models/__init__.py
textformer/models/att_seq2seq.py
textformer/models/conv_seq2seq.py
textformer/models/joint_seq2seq.py
textformer/models/seq2seq.py
textformer/models/transformer.py
textformer/models/decoders/__init__.py
textformer/models/decoders/bi_gru.py
textformer/models/decoders/conv.py
textformer/models/decoders/gru.py
textformer/models/decoders/lstm.py
textformer/models/decoders/self_attention.py
textformer/models/encoders/__init__.py
textformer/models/encoders/bi_gru.py
textformer/models/encoders/conv.py
textformer/models/encoders/gru.py
textformer/models/encoders/lstm.py
textformer/models/encoders/self_attention.py
textformer/models/layers/__init__.py
textformer/models/layers/attention.py
textformer/models/layers/multi_head_attention.py
textformer/models/layers/position_wide_forward.py
textformer/models/layers/residual_attention.py
textformer/utils/__init__.py
textformer/utils/constants.py
textformer/utils/exception.py
textformer/utils/logging.py
textformer/utils/visualization.py
textformer-1.0.1.dist-info/LICENSE
textformer-1.0.1.dist-info/METADATA
textformer-1.0.1.dist-info/WHEEL
textformer-1.0.1.dist-info/top_level.txt
textformer-1.0.1.dist-info/RECORD
