Metadata-Version: 2.1
Name: textformer
Version: 1.0.1
Summary: Transformer-based Text Operators
Home-page: https://github.com/gugarosa/textformer
Author: Gustavo Rosa
Author-email: gustavo.rosa@unesp.br
License: GPL-3.0
Platform: UNKNOWN
Classifier: Development Status :: 5 - Production/Stable
Classifier: Intended Audience :: Developers
Classifier: Intended Audience :: Education
Classifier: Intended Audience :: Science/Research
Classifier: License :: OSI Approved :: GNU General Public License v3 (GPLv3)
Classifier: Programming Language :: Python :: 3.6
Classifier: Programming Language :: Python :: 3.7
Classifier: Programming Language :: Python :: 3.8
Classifier: Topic :: Software Development :: Libraries
Classifier: Topic :: Software Development :: Libraries :: Python Modules
Requires-Dist: coverage (>=5.1)
Requires-Dist: pylint (>=2.5.2)
Requires-Dist: pytest (>=5.4.2)
Requires-Dist: torch (>=1.5.0)
Requires-Dist: torchtext (>=0.6.0)
Requires-Dist: tqdm (>=4.46.0)
Provides-Extra: tests
Requires-Dist: coverage ; extra == 'tests'
Requires-Dist: pytest ; extra == 'tests'
Requires-Dist: pytest-pep8 ; extra == 'tests'
